pandas_categorical/__init__.py
pandas_categorical/py.typed
pandas_categorical/utils.py
pandas_categorical-1.2.0.dist-info/LICENSE
pandas_categorical-1.2.0.dist-info/METADATA
pandas_categorical-1.2.0.dist-info/WHEEL
pandas_categorical-1.2.0.dist-info/RECORD
