Metadata-Version: 2.1
Name: pandas-categorical
Version: 1.2.0
Summary: A set of functions for working with categorical columns in pandas
Home-page: https://github.com/loskost/pandas-categorical
License: MIT
Keywords: data,datascience,pandas
Author: KonstantinLosev
Author-email: loskost@ya.ru
Requires-Python: >=3.7,<3.14
Classifier: License :: OSI Approved :: MIT License
Classifier: Operating System :: OS Independent
Classifier: Programming Language :: Python
Classifier: Programming Language :: Python :: 3
Classifier: Programming Language :: Python :: 3.7
Classifier: Programming Language :: Python :: 3.8
Classifier: Programming Language :: Python :: 3.9
Classifier: Programming Language :: Python :: 3.10
Classifier: Programming Language :: Python :: 3.11
Classifier: Programming Language :: Python :: 3.12
Classifier: Programming Language :: Python :: 3.13
Classifier: Programming Language :: Python :: 3 :: Only
Classifier: Programming Language :: Python :: Implementation :: CPython
Classifier: Topic :: Utilities
Requires-Dist: pandas (>=1.0.0,<1.4.0) ; python_version >= "3.7" and python_version < "3.8"
Requires-Dist: pandas (>=1.4.0,<2.0.0) ; python_version >= "3.8" and python_version < "3.9"
Requires-Dist: pandas (>=2.0.0,<3.0.0) ; python_version >= "3.9" and python_version < "3.14"
Project-URL: Repository, https://github.com/loskost/pandas-categorical
